py_sexpr/__init__.py
py_sexpr/terms.py
py_sexpr/stack_vm/__init__.py
py_sexpr/stack_vm/blockaddr.py
py_sexpr/stack_vm/emit.py
py_sexpr/stack_vm/instr_names.py
py_sexpr/stack_vm/instructions.py
py_sexpr/stack_vm/patch.py
pysexpr-0.6.dist-info/LICENSE
pysexpr-0.6.dist-info/METADATA
pysexpr-0.6.dist-info/WHEEL
pysexpr-0.6.dist-info/entry_points.txt
pysexpr-0.6.dist-info/top_level.txt
pysexpr-0.6.dist-info/RECORD
