Metadata-Version: 2.1
Name: pysexpr
Version: 0.6
Summary: Best s-expression builder targeting Python bytecode
Home-page: https://github.com/thautawarm/PySExpr
Author: thautawarm
Author-email: twshere@outlook.com
License: mit
Keywords: Python,LISP s-expressions,expression-first,compiler,bytecode,metaprogramming
Platform: any
Classifier: Programming Language :: Python :: 3.5
Classifier: Programming Language :: Python :: 3.6
Classifier: Programming Language :: Python :: 3.7
Classifier: Programming Language :: Python :: 3.8
Classifier: Programming Language :: Python :: 3.9
Classifier: Programming Language :: Python :: Implementation :: CPython
Requires-Python: >=3.5.0
Requires-Dist: attrs
Requires-Dist: bytecode (<0.12.0,>=0.10.0)
